pyOpenFEMA/OpenFEMA.py
pyOpenFEMA/__init__.py
pyOpenFEMA/_version.py
pyOpenFEMA/api_url_command_generators.py
pyopenfema-1.1.1.dist-info/licenses/LICENSE.md
pyopenfema-1.1.1.dist-info/METADATA
pyopenfema-1.1.1.dist-info/WHEEL
pyopenfema-1.1.1.dist-info/top_level.txt
pyopenfema-1.1.1.dist-info/RECORD
