Metadata-Version: 2.4
Name: pyOpenFEMA
Version: 1.1.1
Summary: A python package for easily reading OpenFEMA datasets.
Maintainer-email: Keith Doore <keith.doore@fema.dhs.gov>
License: # License
Project-URL: homepage, https://github.com/kjdoore/pyOpenFEMA
Project-URL: repository, https://github.com/kjdoore/pyOpenFEMA.git
Keywords: FEMA,Datasets
Classifier: Programming Language :: Python :: 3
Requires-Python: >=3.9
License-File: LICENSE.md
Requires-Dist: fsspec
Requires-Dist: aiohttp
Requires-Dist: pyarrow
Requires-Dist: pyyaml
Requires-Dist: fastparquet
Requires-Dist: geopandas
Provides-Extra: dev
Requires-Dist: flake8; extra == "dev"
Requires-Dist: ruff; extra == "dev"
Requires-Dist: pytest; extra == "dev"
Requires-Dist: requests_mock; extra == "dev"
Dynamic: license-file
